odoo8_addon_account_bank_statement_import_camt-8.0.0.5.1-py3.8-nspkg.pth
odoo_addons/account_bank_statement_import_camt/README.rst
odoo_addons/account_bank_statement_import_camt/__init__.py
odoo_addons/account_bank_statement_import_camt/__openerp__.py
odoo_addons/account_bank_statement_import_camt/demo/demo_data.xml
odoo_addons/account_bank_statement_import_camt/i18n/account_bank_statement_import_camt.pot
odoo_addons/account_bank_statement_import_camt/i18n/de.po
odoo_addons/account_bank_statement_import_camt/i18n/es.po
odoo_addons/account_bank_statement_import_camt/i18n/fi.po
odoo_addons/account_bank_statement_import_camt/i18n/fr.po
odoo_addons/account_bank_statement_import_camt/i18n/it.po
odoo_addons/account_bank_statement_import_camt/i18n/lt.po
odoo_addons/account_bank_statement_import_camt/i18n/lt_LT.po
odoo_addons/account_bank_statement_import_camt/i18n/nl.po
odoo_addons/account_bank_statement_import_camt/i18n/pt_BR.po
odoo_addons/account_bank_statement_import_camt/i18n/pt_PT.po
odoo_addons/account_bank_statement_import_camt/i18n/sl.po
odoo_addons/account_bank_statement_import_camt/models/__init__.py
odoo_addons/account_bank_statement_import_camt/models/account_bank_statement_import.py
odoo_addons/account_bank_statement_import_camt/models/parser.py
odoo_addons/account_bank_statement_import_camt/static/description/icon.png
odoo_addons/account_bank_statement_import_camt/test_files/test-camt053.xml
odoo_addons/account_bank_statement_import_camt/test_files/test-camt053.zip
odoo_addons/account_bank_statement_import_camt/tests/__init__.py
odoo_addons/account_bank_statement_import_camt/tests/test_import_bank_statement.py
odoo8_addon_account_bank_statement_import_camt-8.0.0.5.1.dist-info/METADATA
odoo8_addon_account_bank_statement_import_camt-8.0.0.5.1.dist-info/WHEEL
odoo8_addon_account_bank_statement_import_camt-8.0.0.5.1.dist-info/namespace_packages.txt
odoo8_addon_account_bank_statement_import_camt-8.0.0.5.1.dist-info/top_level.txt
odoo8_addon_account_bank_statement_import_camt-8.0.0.5.1.dist-info/RECORD
