Metadata-Version: 2.1
Name: odoo8-addon-account-bank-statement-import-camt
Version: 8.0.0.5.1
Summary: Module to import SEPA CAMT.053 Format bank statement files
Home-page: https://github.com/OCA/bank-statement-import
Author: Odoo Community Association (OCA), Therp BV
Author-email: support@odoo-community.org
License: AGPL-3
Platform: UNKNOWN
Classifier: Programming Language :: Python
Classifier: Framework :: Odoo
Classifier: Framework :: Odoo :: 8.0
Classifier: License :: OSI Approved :: GNU Affero General Public License v3
Requires-Python: ~=2.7
Requires-Dist: odoo8-addon-account-bank-statement-import
Requires-Dist: odoo (<9.0a,>=8.0a)
